tuttut/__init__.py
tuttut/midi_tabs_cli.py
tuttut/midi_tabs_gui.py
tuttut/GUI/__init__.py
tuttut/GUI/config.py
tuttut/GUI/dialogs.py
tuttut/GUI/generate.py
tuttut/GUI/gui.py
tuttut/GUI/gui_utils.py
tuttut/GUI/web/Nunito-Light.ttf
tuttut/GUI/web/favicon.ico
tuttut/GUI/web/index.html
tuttut/GUI/web/css/general.css
tuttut/GUI/web/css/main.css
tuttut/GUI/web/css/modal.css
tuttut/GUI/web/img/chevron-square-up.svg
tuttut/GUI/web/img/plus.svg
tuttut/GUI/web/img/remove.svg
tuttut/GUI/web/img/tuttut.png
tuttut/GUI/web/js/configuration.js
tuttut/GUI/web/js/constants.js
tuttut/GUI/web/js/initialise.js
tuttut/GUI/web/js/messages.js
tuttut/GUI/web/js/modal.js
tuttut/GUI/web/js/processing.js
tuttut/GUI/web/js/staticEvents.js
tuttut/GUI/web/js/utils.js
tuttut/logic/__init__.py
tuttut/logic/arrangement.py
tuttut/logic/fretboard.py
tuttut/logic/graph_utils.py
tuttut/logic/midi_utils.py
tuttut/logic/tab.py
tuttut/logic/theory.py
tuttut/logic/validation.py
tuttut-0.0.6.dist-info/METADATA
tuttut-0.0.6.dist-info/WHEEL
tuttut-0.0.6.dist-info/entry_points.txt
tuttut-0.0.6.dist-info/licenses/LICENSE
tuttut-0.0.6.dist-info/RECORD
