Metadata-Version: 2.1
Name: tuttut
Version: 0.0.6
Summary: A package to convert MIDI files to string instrument tabs.
Project-URL: Homepage, https://github.com/natecdr/tuttut
Project-URL: Issues, https://github.com/natecdr/tuttut/issues
Author-email: Nathan Candre <nathan.candre@gmail.com>
License-File: LICENSE
Classifier: License :: OSI Approved :: MIT License
Classifier: Operating System :: OS Independent
Classifier: Programming Language :: Python :: 3
Requires-Python: >=3.8
Requires-Dist: matplotlib==3.5.3
Requires-Dist: networkx==2.8.6
Requires-Dist: numpy==1.23.2
Requires-Dist: pretty-midi==0.2.9
